cachier_client/__init__.py
cachier_client/main.py
cachier_client-0.3.0.dist-info/LICENSE
cachier_client-0.3.0.dist-info/METADATA
cachier_client-0.3.0.dist-info/WHEEL
cachier_client-0.3.0.dist-info/top_level.txt
cachier_client-0.3.0.dist-info/RECORD
