Metadata-Version: 2.1
Name: cachier-client
Version: 0.3.0
Summary: A cachier python client package
Home-page: https://github.com/cachier-cache/cachier-python-client
Author: apinanyogaratnam
Author-email: apinanapinan@icloud.com
Classifier: Programming Language :: Python :: 3
Classifier: License :: OSI Approved :: MIT License
Classifier: Operating System :: OS Independent
Requires-Python: >=3.8
License-File: LICENSE
